presage_physiology_preprocessing/__init__.py
presage_physiology_preprocessing/mediapipefunctions.py
presage_physiology_preprocessing/preprocessing.py
presage_physiology_preprocessing/version.py
Presage_Physiology_Preprocessing-1.2.9.dist-info/LICENSE
Presage_Physiology_Preprocessing-1.2.9.dist-info/METADATA
Presage_Physiology_Preprocessing-1.2.9.dist-info/WHEEL
Presage_Physiology_Preprocessing-1.2.9.dist-info/top_level.txt
Presage_Physiology_Preprocessing-1.2.9.dist-info/RECORD
