Metadata-Version: 2.1
Name: Presage-Physiology-Preprocessing
Version: 1.2.9
Summary: A Python helper package used for preprocessing video before sending it to Presage Technologies Physiology API.
Home-page: https://physiology.presagetech.com/
Author: Presage Technologies
Author-email: support@presagetech.com
License: UNKNOWN
Project-URL: Bug Tracker, https://github.com/Presage-Security/presage_physiology_preprocessing/issues
Platform: UNKNOWN
Classifier: Programming Language :: Python :: 3
Classifier: License :: OSI Approved :: MIT License
Classifier: Operating System :: OS Independent
Requires-Python: >=3.6
Requires-Dist: mediapipe ==0.10.8
Requires-Dist: numpy ==1.23.3
Requires-Dist: ffmpeg-python ==0.2.0
Requires-Dist: opencv-python ==4.10.0.82
